persisted/__init__.py
persisted/bytes.py
persisted/module.py
persisted/persisted.py
persisted/pickle.py
persisted/string.py
persisted-1.0.0b2.dist-info/LICENSE.txt
persisted-1.0.0b2.dist-info/METADATA
persisted-1.0.0b2.dist-info/WHEEL
persisted-1.0.0b2.dist-info/top_level.txt
persisted-1.0.0b2.dist-info/RECORD
