Metadata-Version: 2.1
Name: persisted
Version: 1.0.0b2
Summary: A two-way data persistence framework for watching file changes / updating files based on changes
Home-page: https://github.com/alexkoay/persisted
Author: Alex Koay
Author-email: alexkoay88@gmail.com
License: UNKNOWN
Keywords: persistence watch reload save
Platform: UNKNOWN
Classifier: Development Status :: 4 - Beta
Classifier: Intended Audience :: Developers
Classifier: License :: OSI Approved :: MIT License
Classifier: Operating System :: OS Independent
Classifier: Programming Language :: Python :: 3
Classifier: Programming Language :: Python :: 3.7
Classifier: Programming Language :: Python :: 3.8
Classifier: Programming Language :: Python :: 3.9
Classifier: Programming Language :: Python :: 3.10
Classifier: Programming Language :: Python :: 3 :: Only
Classifier: Topic :: Utilities
Requires-Python: >=3.7, <4
License-File: LICENSE.txt
Provides-Extra: dev
Requires-Dist: black ; extra == 'dev'
Requires-Dist: mypy ; extra == 'dev'
Requires-Dist: isort ; extra == 'dev'
